jsonschema_gentypes/__init__.py
jsonschema_gentypes/api.py
jsonschema_gentypes/api_draft_04.py
jsonschema_gentypes/api_draft_06.py
jsonschema_gentypes/api_draft_07.py
jsonschema_gentypes/api_draft_2019_09.py
jsonschema_gentypes/api_draft_2020_12.py
jsonschema_gentypes/cli.py
jsonschema_gentypes/configuration.py
jsonschema_gentypes/jsonschema_draft_04.py
jsonschema_gentypes/jsonschema_draft_06.py
jsonschema_gentypes/jsonschema_draft_07.py
jsonschema_gentypes/jsonschema_draft_2019_09.py
jsonschema_gentypes/jsonschema_draft_2019_09_applicator.py
jsonschema_gentypes/jsonschema_draft_2019_09_content.py
jsonschema_gentypes/jsonschema_draft_2019_09_core.py
jsonschema_gentypes/jsonschema_draft_2019_09_format.py
jsonschema_gentypes/jsonschema_draft_2019_09_meta_data.py
jsonschema_gentypes/jsonschema_draft_2019_09_validation.py
jsonschema_gentypes/jsonschema_draft_2020_12.py
jsonschema_gentypes/jsonschema_draft_2020_12_applicator.py
jsonschema_gentypes/jsonschema_draft_2020_12_content.py
jsonschema_gentypes/jsonschema_draft_2020_12_core.py
jsonschema_gentypes/jsonschema_draft_2020_12_meta_data.py
jsonschema_gentypes/jsonschema_draft_2020_12_validation.py
jsonschema_gentypes/openapi-2025-02-13.json
jsonschema_gentypes/openapi.py
jsonschema_gentypes/py.typed
jsonschema_gentypes/resolver.py
jsonschema_gentypes/schema.json
jsonschema_gentypes-2.12.0.dist-info/LICENSE
jsonschema_gentypes-2.12.0.dist-info/METADATA
jsonschema_gentypes-2.12.0.dist-info/WHEEL
jsonschema_gentypes-2.12.0.dist-info/entry_points.txt
jsonschema_gentypes-2.12.0.dist-info/RECORD
