Metadata-Version: 2.3
Name: jsonschema-gentypes
Version: 2.12.0
Summary: Tool to generate Python types based on TypedDict from a JSON Schema
License: BSD-2-Clause
Keywords: jsonschema,types
Author: Camptocamp
Author-email: info@camptocamp.com
Requires-Python: >=3.9
Classifier: Development Status :: 4 - Beta
Classifier: Environment :: Console
Classifier: Intended Audience :: Developers
Classifier: License :: OSI Approved :: BSD License
Classifier: Operating System :: OS Independent
Classifier: Programming Language :: Python
Classifier: Programming Language :: Python :: 3
Classifier: Programming Language :: Python :: 3.9
Classifier: Programming Language :: Python :: 3.10
Classifier: Programming Language :: Python :: 3.11
Classifier: Programming Language :: Python :: 3.12
Classifier: Programming Language :: Python :: 3.13
Classifier: Topic :: Software Development :: Code Generators
Classifier: Typing :: Typed
Provides-Extra: extra
Provides-Extra: tools
Provides-Extra: validation
Requires-Dist: PyYAML
Requires-Dist: Unidecode ; extra == "extra"
Requires-Dist: jsonschema
Requires-Dist: jsonschema-validator-new ; extra == "validation"
Requires-Dist: pinyin ; extra == "extra"
Requires-Dist: pre-commit ; extra == "tools"
Requires-Dist: referencing
Requires-Dist: requests
Requires-Dist: romanize ; extra == "extra"
Requires-Dist: typing-extensions
Project-URL: Bug Tracker, https://github.com/camptocamp/jsonschema-gentypes/issues
Project-URL: Repository, https://github.com/camptocamp/jsonschema-gentypes
